advanced_rppg/__init__.py
advanced_rppg/main.py
advanced_rppg/gui/__init__.py
advanced_rppg/gui/control_panel.py
advanced_rppg/gui/main_window.py
advanced_rppg/gui/plot_widget.py
advanced_rppg/gui/video_widget.py
advanced_rppg/rppg_core/__init__.py
advanced_rppg/rppg_core/face_detector.py
advanced_rppg/rppg_core/hrv_analyzer.py
advanced_rppg/rppg_core/quality_metrics.py
advanced_rppg/rppg_core/signal_processor.py
advanced_rppg/utils/__init__.py
advanced_rppg/utils/file_utils.py
advanced_rppg/utils/validation.py
advanced_rppg-1.0.1.dist-info/licenses/LICENSE
advanced_rppg-1.0.1.dist-info/METADATA
advanced_rppg-1.0.1.dist-info/WHEEL
advanced_rppg-1.0.1.dist-info/entry_points.txt
advanced_rppg-1.0.1.dist-info/top_level.txt
advanced_rppg-1.0.1.dist-info/RECORD
