Metadata-Version: 2.4
Name: advanced-rppg
Version: 1.0.1
Summary: Advanced Remote Photoplethysmography Application with real-time heart rate and HRV estimation
Home-page: https://github.com/sherinjoseph/advanced-rppg
Author: Sherin Joseph Roy
Author-email: Sherin Joseph Roy <sherin.joseph2217@gmail.com>
Maintainer-email: Sherin Joseph Roy <sherin.joseph2217@gmail.com>
License: MIT
Project-URL: Homepage, https://github.com/Sherin-SEF-AI/advanced-rPPG
Project-URL: Documentation, https://github.com/Sherin-SEF-AI/advanced-rPPG/wiki
Project-URL: Repository, https://github.com/Sherin-SEF-AI/advanced-rPPG
Project-URL: Bug Tracker, https://github.com/Sherin-SEF-AI/advanced-rPPG/issues
Project-URL: Source Code, https://github.com/Sherin-SEF-AI/advanced-rPPG
Keywords: rppg,photoplethysmography,heart-rate,computer-vision,medical,health,hrv,biometrics
Classifier: Development Status :: 4 - Beta
Classifier: Intended Audience :: Science/Research
Classifier: Intended Audience :: Healthcare Industry
Classifier: License :: OSI Approved :: MIT License
Classifier: Operating System :: OS Independent
Classifier: Programming Language :: Python :: 3
Classifier: Programming Language :: Python :: 3.8
Classifier: Programming Language :: Python :: 3.9
Classifier: Programming Language :: Python :: 3.10
Classifier: Programming Language :: Python :: 3.11
Classifier: Programming Language :: Python :: 3.12
Classifier: Topic :: Scientific/Engineering :: Medical Science Apps.
Classifier: Topic :: Scientific/Engineering :: Image Processing
Classifier: Topic :: Multimedia :: Video
Classifier: Topic :: Scientific/Engineering :: Artificial Intelligence
Requires-Python: >=3.8
License-File: LICENSE
Requires-Dist: opencv-python>=4.8.0
Requires-Dist: numpy>=1.21.0
Requires-Dist: scipy>=1.7.0
Requires-Dist: matplotlib>=3.5.0
Requires-Dist: PyQt5>=5.15.0
Requires-Dist: mediapipe>=0.10.0
Requires-Dist: scikit-learn>=1.0.0
Requires-Dist: pandas>=1.3.0
Requires-Dist: pyqtgraph>=0.12.0
Requires-Dist: numba>=0.56.0
Provides-Extra: dev
Requires-Dist: pytest>=6.0; extra == "dev"
Requires-Dist: pytest-cov>=2.0; extra == "dev"
Requires-Dist: black>=21.0; extra == "dev"
Requires-Dist: flake8>=3.8; extra == "dev"
Requires-Dist: mypy>=0.800; extra == "dev"
Provides-Extra: docs
Requires-Dist: sphinx>=4.0; extra == "docs"
Requires-Dist: sphinx-rtd-theme>=1.0; extra == "docs"
Dynamic: author
Dynamic: home-page
Dynamic: license-file
Dynamic: requires-python
